kaggle_downloader/__init__.py
kaggle_downloader/kaggle_downloader.py
kaggle_downloader/main.py
kaggle_downloader-1.0.2.dist-info/entry_points.txt
kaggle_downloader-1.0.2.dist-info/LICENSE
kaggle_downloader-1.0.2.dist-info/WHEEL
kaggle_downloader-1.0.2.dist-info/METADATA
kaggle_downloader-1.0.2.dist-info/RECORD
