Metadata-Version: 2.1
Name: kaggle-downloader
Version: 1.0.2
Summary: Download kernels from Kaggle.
Home-page: https://github.com/lars-reimann/kaggle-downloader
License: MIT
Keywords: kaggle,machine-learning
Author: Lars Reimann
Author-email: mail@larsreimann.com
Requires-Python: >=3.9,<4.0
Classifier: License :: OSI Approved :: MIT License
Classifier: Programming Language :: Python :: 3
Classifier: Programming Language :: Python :: 3.9
Requires-Dist: jupyter (>=1.0.0,<2.0.0)
Requires-Dist: kaggle (>=1.5.12,<2.0.0)
Requires-Dist: nbconvert (>=6.1.0,<7.0.0)
Requires-Dist: nbformat (>=5.1.3,<6.0.0)
Project-URL: Repository, https://github.com/lars-reimann/kaggle-downloader
